faststack/__init__.py
faststack/cli.py
faststack/healthcheck.py
faststack/orm.py
faststack/py.typed
faststack/util.py
faststack/apps/README.md
faststack/apps/__init__.py
faststack/apps/fastapi_app.py
faststack/apps/ioc.py
faststack/apps/settings.py
faststack-0.5.0.dist-info/METADATA
faststack-0.5.0.dist-info/WHEEL
faststack-0.5.0.dist-info/licenses/LICENSE.md
faststack-0.5.0.dist-info/RECORD
