Metadata-Version: 2.4
Name: faststack
Version: 0.5.0
Summary: Common utilities for FastAPI apps
Project-URL: Homepage, https://github.com/rmasters/faststack
Project-URL: Issues, https://github.com/rmasters/faststack/issues
Author-email: Ross Masters <ross@rossmasters.com>
License-File: LICENSE.md
Classifier: Development Status :: 3 - Alpha
Classifier: Framework :: FastAPI
Classifier: Intended Audience :: Developers
Classifier: License :: OSI Approved :: MIT License
Classifier: Operating System :: OS Independent
Classifier: Programming Language :: Python :: 3
Classifier: Programming Language :: Python :: 3 :: Only
Classifier: Programming Language :: Python :: 3.12
Classifier: Programming Language :: Python :: 3.13
Classifier: Topic :: Internet :: WWW/HTTP
Classifier: Topic :: Internet :: WWW/HTTP :: WSGI :: Middleware
Classifier: Typing :: Typed
Requires-Python: <4.0,>=3.12
Requires-Dist: asyncer<1.0,>=0.0.7
Requires-Dist: fastapi<1.0,>=0.111.0
Requires-Dist: pydantic-settings>=2.6.1
Requires-Dist: sqlmodel<1.0,>=0.0.22
Requires-Dist: that-depends<3.0,>=2.0.0
Requires-Dist: typer<1.0,>=0.12.3
